logfmter/__init__.py
logfmter/formatter.py
logfmter/py.typed
logfmter-0.0.11.dist-info/licenses/LICENSE.txt
logfmter-0.0.11.dist-info/METADATA
logfmter-0.0.11.dist-info/WHEEL
logfmter-0.0.11.dist-info/top_level.txt
logfmter-0.0.11.dist-info/RECORD
