Metadata-Version: 2.4
Name: logfmter
Version: 0.0.11
Summary: A Python package which supports global logfmt formatted logging.
Home-page: https://github.com/josheppinette/python-logfmter
Author: Joshua Taylor Eppinette
Author-email: josheppinette@gmail.com
License: MIT
Requires-Python: >=3.9
License-File: LICENSE.txt
Dynamic: license-file
